sdnq/__init__.py
sdnq/common.py
sdnq/dequantizer.py
sdnq/file_loader.py
sdnq/forward.py
sdnq/loader.py
sdnq/packed_float.py
sdnq/packed_int.py
sdnq/quantizer.py
sdnq/sdnext.py
sdnq/triton_mm.py
sdnq/layers/__init__.py
sdnq/layers/conv/conv_fp16.py
sdnq/layers/conv/conv_fp8.py
sdnq/layers/conv/conv_fp8_tensorwise.py
sdnq/layers/conv/conv_int8.py
sdnq/layers/conv/forward.py
sdnq/layers/linear/forward.py
sdnq/layers/linear/linear_fp16.py
sdnq/layers/linear/linear_fp8.py
sdnq/layers/linear/linear_fp8_tensorwise.py
sdnq/layers/linear/linear_int8.py
sdnq/optim/__init__.py
sdnq/optim/adafactor.py
sdnq/optim/adamw.py
sdnq/optim/came.py
sdnq/optim/lion.py
sdnq/optim/muon.py
sdnq/optim/optimizer.py
sdnq/optim/utils.py
sdnq/training/__init__.py
sdnq/training/forward.py
sdnq/training/tensor.py
sdnq/training/layers/linear/forward.py
sdnq/training/layers/linear/linear_fp16.py
sdnq/training/layers/linear/linear_fp16_ckpt.py
sdnq/training/layers/linear/linear_fp16_dynamic.py
sdnq/training/layers/linear/linear_fp16_dynamic_ckpt.py
sdnq/training/layers/linear/linear_fp8.py
sdnq/training/layers/linear/linear_fp8_ckpt.py
sdnq/training/layers/linear/linear_fp8_dynamic.py
sdnq/training/layers/linear/linear_fp8_dynamic_ckpt.py
sdnq/training/layers/linear/linear_fp8_tensorwise.py
sdnq/training/layers/linear/linear_fp8_tensorwise_ckpt.py
sdnq/training/layers/linear/linear_fp8_tensorwise_dynamic.py
sdnq/training/layers/linear/linear_fp8_tensorwise_dynamic_ckpt.py
sdnq/training/layers/linear/linear_int8.py
sdnq/training/layers/linear/linear_int8_ckpt.py
sdnq/training/layers/linear/linear_int8_dynamic.py
sdnq/training/layers/linear/linear_int8_dynamic_ckpt.py
sdnq-0.1.4.dist-info/licenses/LICENSE
sdnq-0.1.4.dist-info/METADATA
sdnq-0.1.4.dist-info/WHEEL
sdnq-0.1.4.dist-info/top_level.txt
sdnq-0.1.4.dist-info/RECORD
