Metadata-Version: 2.4
Name: sdnq
Version: 0.1.4
Summary: SD.Next Quantization Engine
Author-email: Disty0 <disty@disty.xyz>
License-Expression: GPL-3.0-only
Project-URL: Homepage, https://github.com/Disty0/sdnq
Project-URL: Issues, https://github.com/Disty0/sdnq/issues
Classifier: Programming Language :: Python :: 3
Classifier: Operating System :: OS Independent
Requires-Python: >=3.10
License-File: LICENSE
Requires-Dist: torch
Requires-Dist: diffusers
Requires-Dist: transformers
Requires-Dist: accelerate
Dynamic: license-file
